{
  "categories": [
    {
      "name": "Video games",
      "icon": "Gamepad2",
      "id": "video_games",
      "categories": [
        {
          "name": "Mario Universe",
          "icon": "Star",
          "id": "mario_universe",
          "words": [
            "Mario",
            "Luigi",
            "Princess Peach",
            "Bowser",
            "Bowser Jr.",
            "Donkey Kong",
            "Diddy Kong",
            "Toad",
            "Yoshi",
            "Wario",
            "Waluigi",
            "Goomba",
            "Koopa Troopa",
            "Dry Bones",
            "Shy Guy",
            "Boo",
            "Bullet Bill",
            "Bob-omb",
            "Hammer Bro",
            "Lakitu",
            "Piranha Plant",
            "Nabbit",
            "Cappy",
            "Super Mario Odyssey",
            "Mario Kart",
            "Mario Party",
            "Luigi’s Mansion",
            "Mushroom Kingdom",
            "Rainbow Road",
            "Coconut Mall",
            "Moo Moo",
            "Mushroom",
            "Fire Flower",
            "Ice Flower",
            "Super Star",
            "Propeller Mushroom",
            "Cat Suit",
            "Moon",
            "Shell",
            "Banana Peel",
            "Blooper Ink",
            "Lightning Bolt",
            "Super Horn",
            "Fake Item Box",
            "Mario Movie",
            "Kamek",
            "Warp Pipe",
            "Question Block",
            "Brick Block",
            "Flagpole",
            "Mama mia"
          ]
        },
        {
          "name": "Super Smash Bros.",
          "icon": "Gamepad",
          "id": "super_smash_bros",
          "words": [
            "Spike",
            "Shield Break",
            "Edge Guard",
            "Melee",
            "3-Stock",
            "Kirby",
            "Animal Crossing",
            "Splatoon",
            "Nintendo Direct",
            "Amiibo",
            "Sonic",
            "Knuckles",
            "Story Mode",
            "Master Hand",
            "Samus",
            "Yoshi",
            "Fox",
            "Pikachu",
            "Captain Falcon",
            "Jigglypuff",
            "Peach",
            "Daisy",
            "Bowser",
            "Ice Climbers",
            "Sheik",
            "Zelda",
            "Falco",
            "Marth",
            "Lucina",
            "Ganondorf",
            "Mewtwo",
            "Mr. Game & Watch",
            "Meta Knight",
            "Pit",
            "Snake",
            "Ike",
            "Pokémon Trainer",
            "Diddy Kong",
            "King Dedede",
            "Olimar",
            "Lucario",
            "R.O.B.",
            "Villager",
            "Mega Man",
            "Wii Fit Trainer",
            "Little Mac",
            "Greninja",
            "Palutena",
            "Pac-Man",
            "Shulk",
            "Duck Hunt",
            "Ryu",
            "Ken",
            "Cloud",
            "Bayonetta",
            "Inkling",
            "Ridley",
            "King K. Rool",
            "Incineroar",
            "Piranha Plant",
            "Banjo & Kazooie",
            "Min Min",
            "Steve",
            "Ness",
            "Smash Ball",
            "Air Dodge",
            "Kill Percent",
            "Projectile Reflector",
            "Poké Ball",
            "Fire Flower",
            "Home-Run Bat",
            "Hammer",
            "Banana Peel",
            "Fake Smash Ball",
            "Bullet Bill",
            "Soccer Ball",
            "Spicy Curry"
          ]
        },
        {
          "name": "Pokémon",
          "icon": "CircleDot",
          "id": "pokmon",
          "words": [
            "Pikachu",
            "Charizard",
            "Bulbasaur",
            "Squirtle",
            "Eevee",
            "Gengar",
            "Lucario",
            "Rayquaza",
            "Arceus",
            "Gyarados",
            "Scizor",
            "Wooper",
            "Psyduck",
            "Ash Ketchum",
            "Team Rocket",
            "Meowth",
            "Professor Oak",
            "Nurse Joy",
            "Misty",
            "Brock",
            "Cynthia",
            "Poké Ball",
            "Evolution Stone",
            "Mega Evolution",
            "Pokédex",
            "Gotta Catch ’Em All",
            "Who’s That Pokémon",
            "Detective Pikachu",
            "I Choose You",
            "Vaporeon Copypasta",
            "Pokémon Red/Blue/Yellow",
            "Pokémon XYZ",
            "Pokémon Sun/Moon",
            "Pokémon Sword/Shield",
            "Pokémon Legends: Arceus",
            "Pokémon Scarlet/Violet",
            "Pokémon GO",
            "Pokémon Cards",
            "Gardevoir",
            "Lopuny",
            "Snorlax",
            "Ditto",
            "Greninja",
            "Jigglypuff",
            "Pokimane",
            "Ludwig"
          ]
        },
        {
          "name": "Zelda",
          "icon": "Sword",
          "id": "zelda",
          "words": [
            "Korok",
            "Rupee",
            "Master Sword",
            "Blood Moon",
            "Shrine",
            "Hyrule",
            "Link",
            "Windbomb",
            "Divine Beasts",
            "Sheikah",
            "Sky Island",
            "Bokoblin",
            "Lynel",
            "Guardian",
            "Calamity Ganon",
            "Ganondorf",
            "Yiga Clan",
            "Fairy Fountain",
            "Lost Woods",
            "Gerudo Desert",
            "Flurry Rush",
            "Shield Surfing",
            "Mapping Towers",
            "Ocarina of Time",
            "Majora’s Mask"
          ]
        },
        {
          "name": "Shooter",
          "icon": "Crosshair",
          "id": "shooter",
          "words": [
            "Call of Duty",
            "Quickscope",
            "CSGO",
            "GW2",
            "Shell Shockers",
            "Apex Legends",
            "Fortnite",
            "1v1 LOL",
            "Valorant",
            "Overwatch 2",
            "Rainbow Six Siege",
            "Warzone",
            "PUBG",
            "Halo",
            "Team Fortress 2",
            "Far Cry",
            "Pixel Gun 3D",
            "War Robots",
            "Splatoon",
            "Valve Games"
          ]
        },
        {
          "name": "Fortnite",
          "icon": "Target",
          "id": "fortnite",
          "words": [
            "Chug Jug",
            "Slurp Juice",
            "Reboot Card",
            "Shield Bubble",
            "Storm",
            "Cranking 90s",
            "Ninja",
            "Where We Dropping Boys?",
            "Travis Scott",
            "Default Dance",
            "Fish Stick",
            "Peely",
            "Peter Griffin",
            "Bus Driver",
            "Peanut Butter",
            "Tilted Towers",
            "Live Event",
            "Infinity Sword"
          ]
        },
        {
          "name": "Minecraft",
          "icon": "Box",
          "id": "minecraft",
          "words": [
            "Creeper",
            "Redstone",
            "Nether",
            "Elytra",
            "Enderman",
            "Steve",
            "Chicken Jockey",
            "Dream",
            "Technoblade",
            "Totem of Undying",
            "Hardcore World",
            "AFK Farm",
            "Seed",
            "Pearl",
            "Hardcore",
            "SMP",
            "Speedrun",
            "Hot Lava Chicken",
            "Herobrine",
            "Monster School",
            "Minecraft Story Mode",
            "Iron Golem",
            "Mace",
            "Spawner",
            "Ender Dragon",
            "Wither",
            "A Minecraft movie",
            "Zombie",
            "Skeleton",
            "Spider",
            "Ghast",
            "Woodland Mansion",
            "Ocean Monument",
            "Mooshroom",
            "Witch",
            "Diamond",
            "Beacon",
            "Enchanted Golden Apple",
            "Trident",
            "TNT",
            "Enchanting",
            "XP Farm",
            "Villager Trading Hall",
            "Flying Machine",
            "Bed Explosion",
            "MLG Clutch",
            "Bedrock",
            "April Fools Snapshot",
            "Skyblock",
            "Hypixel",
            "BedWars",
            "Parkour",
            "Build Battle",
            "Minecraft Manhunt",
            "Void",
            "Never Dig Straight Down"
          ]
        },
        {
          "name": "Indie/Horror",
          "icon": "Sprout",
          "id": "indie__horror",
          "words": [
            "Hollow Knight",
            "Rain World",
            "Cuphead",
            "Terraria",
            "It takes two",
            "Only up",
            "Granny",
            "FNAF",
            "Animatronics",
            "Security Camera",
            "Toy Chika",
            "Granny",
            "Baldi’s Basics",
            "Among Us",
            "Phasmophobia",
            "R.E.P.O",
            "Poppy Playtime",
            "Lethal Company",
            "Outlast",
            "Subnautica",
            "Undertale",
            "Dead Cells",
            "Escape the Backrooms",
            "Liminal Space",
            "Doors"
          ]
        },
        {
          "name": "Brawl Stars",
          "icon": "Swords",
          "id": "brawl_stars",
          "words": [
            "Shelly",
            "Colt",
            "Bull",
            "Brock",
            "Rico",
            "Spike",
            "Leon",
            "Jessie",
            "Nita",
            "Dynamike",
            "El Primo",
            "Poco",
            "Barley",
            "Darryl",
            "Penny",
            "Frank",
            "Mortis",
            "Tick",
            "Surge",
            "Buzz",
            "Fang",
            "Mandy",
            "Gadget",
            "Star Power",
            "Hypercharge",
            "Showdown",
            "Gem Grab",
            "Brawl Ball",
            "Heist",
            "Bounty",
            "Hot Zone",
            "Knockout",
            "Power Cubes",
            "Bush Camping",
            "Starr Drops",
            "Mega Box"
          ]
        },
        {
          "name": "Clash Royale",
          "icon": "Crown",
          "id": "clash_royal",
          "words": [
            "Pancakes",
            "Elixir",
            "Hog Rider",
            "Log Bait",
            "Mega Knight",
            "X-Bow",
            "2.6",
            "Jynxzi",
            "Mohamed Light",
            "Ryley",
            "Heheheha Emote",
            "BM Emoting",
            "Overtime",
            "King Tower Activation",
            "Merge Tactics",
            "Princess",
            "Golem",
            "Elite Barbarians",
            "Royal Recruits",
            "Sparky",
            "Inferno Dragon",
            "Rocket",
            "Zap",
            "Graveyard",
            "Golden Knight",
            "Miner",
            "Monk",
            "Evolution",
            "Hero",
            "Champion",
            "Little Prince",
            "Mini P.E.K.K.A",
            "Prince",
            "Dart Goblin",
            "Bowler",
            "Musketeer",
            "Firecracker",
            "Wall Breakers",
            "Prediction",
            "Boss Bandit",
            "Elixir Golem",
            "Electro Giant",
            "Royal",
            "Giant",
            "Goblin Gang",
            "Skeleton Army",
            "Ice Spirit",
            "Credit Card",
            "Evo Wizard",
            "Pass Royal"
          ]
        },
        {
          "name": "Mobile/Arcade",
          "icon": "Smartphone",
          "id": "mobile___arcade",
          "words": [
            "Genshin Impact",
            "Plants vs. Zombies",
            "Fall Guys",
            "Among Us",
            "Subway Surfers",
            "Geometry Dash",
            "Pac-Man",
            "Space Invaders",
            "Donkey Kong",
            "Temple Run",
            "Crossy Road",
            "Fruit Ninja",
            "Cut the Rope",
            "Where’s My Water",
            "Angry Birds",
            "Flappy Bird",
            "Jetpack Joyride",
            "Doodle Jump",
            "Talking Tom",
            "Clash of Clans",
            "Brawl Stars",
            "Candy Crush",
            "Piano Tiles",
            "Badland",
            "Bowmasters",
            "Paper.io",
            "Slither.io",
            "Hungry Shark",
            "Bloons",
            "Hole.io",
            "Voodoo Games",
            "Aquapark.io",
            "Kick the Buddy",
            "Sonic Dash",
            "Minion Rush",
            "Asphalt",
            "Clash Royale",
            "My Singing Monsters",
            "Pixel Gun 3D",
            "Dino Run",
            "Street Fighter",
            "Basketball Stars",
            "BitLife",
            "Pokémon GO",
            "Rocket League",
            "War Robots",
            "PUBG",
            "Fallout Shelter",
            "League of Legends"
          ]
        },
        {
          "name": "Roblox",
          "icon": "Bot",
          "id": "roblox",
          "words": [
            "Obby",
            "Robux",
            "Spin a Baddie",
            "Blox Fruits",
            "Adopt Me",
            "Doors",
            "BedWars",
            "Murder Mystery",
            "Helen Keller",
            "Hide and Seek",
            "Tycoon",
            "Jail Break",
            "Bee Swarm",
            "Pets",
            "Trading",
            "Sheriff",
            "Devil Fruit",
            "Conveyor belt",
            "Spawn Point",
            "Oof",
            "Bacon Hair",
            "Game pass",
            "Natural Disaster Survival",
            "Grow a Garden",
            "Build a boat for treasure"
          ]
        },
        {
          "name": "VR",
          "icon": "Glasses",
          "id": "vr",
          "words": [
            "Phasmophobia",
            "Among Us",
            "FNaF",
            "Minecraft",
            "Beat Saber",
            "Gorilla Tag",
            "Half-Life Alyx",
            "VRChat",
            "Boneworks",
            "Blade and Sorcery",
            "Superhot VR",
            "Rec Room",
            "Pavlov",
            "Job Simulator"
          ]
        },
        {
          "name": "PlayStation Games",
          "icon": "Gamepad2",
          "id": "playstation_games",
          "words": [
            "God of War",
            "The Last of Us",
            "Uncharted",
            "Horizon Zero Dawn",
            "Ghost of Tsushima",
            "Gran Turismo",
            "Marvel’s Spider-Man",
            "FIFA",
            "NBA 2K",
            "Rocket League",
            "LittleBigPlanet",
            "Detroit: Become Human",
            "Elden Ring",
            "Red Dead Redemption 2",
            "Call of Duty",
            "Fortnite",
            "Apex Legends",
            "Fall Guys",
            "GTA V",
            "Among Us",
            "Rainbow Six Siege",
            "Valorant",
            "Overwatch 2",
            "Subnautica",
            "Street Fighter",
            "Mortal Kombat",
            "Cuphead",
            "Hollow Knight",
            "Undertale",
            "FNAF",
            "Poppy Playtime",
            "Astro Bot",
            "Fallout"
          ]
        }
      ]
    },
    {
      "name": "Memes",
      "icon": "Laugh",
      "id": "memes",
      "categories": [
        {
          "name": "Generational",
          "icon": "Clock",
          "id": "generational",
          "words": [
            "Rickroll",
            "Trollface",
            "Success Kid",
            "Nyan Cat",
            "Harlem Shake",
            "Gangnam Style",
            "Doge",
            "Pepe the Frog",
            "Vine",
            "Drake",
            "This Is Fine Dog",
            "Uno Reverse Card",
            "Michael Jordan",
            "Whassaaaap",
            "Why Are You Running",
            "Do You Know Da Wae",
            "No God Please No",
            "Leonardo DiCaprio",
            "The Rock",
            "John Cena",
            "SpongeBob",
            "South Park",
            "Family Guy",
            "Shrek",
            "Matrix",
            "Spider-Man",
            "Willem Dafoe",
            "Mr. Bean",
            "Key & Peele",
            "Beetlejuice",
            "The Backrooms",
            "Mandela Effect",
            "Stonks",
            "Blue or Gold Dress",
            "Leeroy Jenkins",
            "Crazy Frog",
            "Fat Chungus",
            "Wise Mystical Tree",
            "Are Ya Winning Son",
            "3 Spidermen Pointing at Each Other",
            "Ronaldo Drinking Coke",
            "Khaby Lame",
            "Gigachad",
            "Soyjak/Wojak",
            "Mr. Incredible memes",
            "Charlie Bit My Finger",
            "67",
            "Galaxy Brain",
            "Noice",
            "GTA Wasted",
            "Charlie Kirk",
            "Omegle",
            "Massive",
            "Joe mama",
            "Shaq Time Out"
          ]
        },
        {
          "name": "Characters",
          "icon": "Users",
          "id": "characters",
          "words": [
            "Pepe the Frog",
            "Grimace Shake",
            "Kai Cenat",
            "MrBeast",
            "Jake Paul",
            "Logan Paul",
            "Druski",
            "K-Pop Demon Hunters",
            "Chicken Jockey",
            "Will Smith",
            "Dudeman",
            "City Boy",
            "Seong Gi-hun (Squid Game)",
            "Vecna (Stranger Things)",
            "IShowSpeed",
            "Homelander",
            "SpongeBob",
            "Beetlejuice",
            "Ronaldo",
            "Zach D Films",
            "DJ Babyface",
            "Friggin Packet Yo",
            "Chopped Chin",
            "Khaby Lame",
            "Officer Nate Higgerson",
            "Nikocado Avocado",
            "John Pork",
            "P. Diddy",
            "Luigi Mangione",
            "Doakes (Dexter)",
            "Hassan",
            "Homer Simpson",
            "Gumball",
            "FlightReacts",
            "LeBron",
            "Asian Bobby",
            "Somali",
            "Bart Simpson",
            "Travis Scott",
            "Kanye",
            "Red Angry Bird",
            "Steve (Minecraft Movie)",
            "Erika Kirk",
            "Dr. House",
            "Megamind",
            "Jarvis",
            "Larry",
            "The Genie",
            "Burger King Plane Guy",
            "Coldplay",
            "Cheating CEOs",
            "Turkish Olympic Shooter",
            "Omni-Man (Invincible)",
            "Jynxzi",
            "Charlie Kirk",
            "Leonardo DiCaprio",
            "The Rock",
            "John Cena",
            "Mr. Bean",
            "Smurf Cat",
            "Beluga (Youtuber)",
            "Jonkler",
            "Among Us Crewmate",
            "Michael (The Office)",
            "Bad Luck Brian",
            "Supa Hot Fire",
            "Tung Tung Tung Sahur",
            "Tralalero Tralala",
            "Big Chungus",
            "Disaster Girl",
            "Wojak/Soyjak",
            "Chad",
            "Herobrine",
            "Patrick Bateman",
            "Chill Guy",
            "Mr. Incredible",
            "MeatCanyon",
            "Willem Dafoe",
            "Flint Lockwood",
            "Gru",
            "Minions",
            "Po",
            "Master Oogway",
            "Keanu Reeves",
            "Walter White",
            "Saul Goodman",
            "Darth Vader",
            "Ryan Gosling",
            "Christian Bale",
            "Jim Carrey",
            "Nicolas Cage",
            "Jack Sparrow",
            "Joker",
            "Hawk Tuah Girl",
            "Vexbolts",
            "Jack Black",
            "Skibidi Toilet",
            "Gnome",
            "Pedro Pascal",
            "Morgan Freeman",
            "Tom Holland",
            "Andrew Garfield",
            "Tobey Maguire",
            "Jackie Chan",
            "Danny DeVito",
            "Arnold Schwarzenegger",
            "Vin Diesel",
            "Cillian Murphy",
            "Ryan Reynolds",
            "J.K. Simmons",
            "Hide the Pain Harold",
            "This Is Fine Dog",
            "SCPs",
            "Brian (Family Guy)",
            "Peter (Family Guy)",
            "Weeb",
            "67 Mason",
            "Tim Cheese",
            "Taylor Swift",
            "Greta Thunberg",
            "Trump",
            "Epstein",
            "Shaq",
            "Ashton Hall",
            "Ted the Bear",
            "Pingu",
            "Hampter",
            "Sydney Sweeny",
            "Mike Tyson",
            "King Von",
            "Markiplier"
          ]
        },
        {
          "name": "Brainrot",
          "icon": "Zap",
          "id": "brainrot",
          "words": [
            "Touch Grass",
            "Main Character Aura",
            "Ragebait",
            "Ohio",
            "Gyatt",
            "Fanum Tax",
            "Rizz",
            "Skibidi",
            "iPad Kid",
            "Discord Mod",
            "Karma",
            "Well Well Well",
            "AI Presidents Gaming",
            "67",
            "Performative Male",
            "Japan",
            "Yo Gurt",
            "Low Taper Fade",
            "41",
            "Chud",
            "Barbershop Haircut",
            "F Students Are Inventors",
            "Calc",
            "Property in Egypt",
            "Mog/Mew",
            "I’ve Played These Games Before",
            "Costco Guys",
            "Hawk Tuah",
            "Drippy Cheese",
            "Rizzler",
            "Huzz",
            "Vexbolts",
            "Oi Oi Oi",
            "Knee Surgery",
            "Chill Guy",
            "I Am a Surgeon",
            "There’s Nothing We Can Do (Napoleon)",
            "Tung Tung Tung Sahur",
            "Canon Event",
            "YouTube Shorts Comment Section",
            "Supa Hot Fire",
            "Diabolical Willem Dafoe Memes",
            "It’s Morbin’ Time",
            "Chinese Eggman",
            "“Father? What’s that?”",
            "Bird Game 3",
            "But Why Penguin",
            "Workin on a Weekend Like Usual",
            "Indian Dating Show",
            "Gay Son or Thot Daughter",
            "Dinner With Jay-Z",
            "Not Quite My Tempo",
            "I Was Lightning Before the Thunder",
            "Are You Ladies Alright?",
            "Sneaky Golem",
            "TikTok Rizz Party",
            "Quandary Dingle",
            "My Granny Got Hit by a Bazooka",
            "Indian Street Food",
            "Prime",
            "Sigma",
            "Phonk",
            "Mango",
            "Benjammins GIFs",
            "Gabagool",
            "Meta Glasses",
            "Epstein",
            "Hoopify",
            "George Floyd",
            "English or Spanish",
            "My Momma Kinda Homeless",
            "Sus",
            "Mustard",
            "The “Cylinder”",
            "Goon",
            "Elite Ball Knowledge",
            "John Pork",
            "White Monster",
            "Thousand Yard Stare",
            "All Roads Lead to Rome",
            "Gassy Incredible",
            "Uncanny Mr. Incredible",
            "You Are My Sunshine LeBron",
            "NPC Livestream",
            "Light Skin Stare",
            "Subway Surfers Split Screen",
            "Minecraft Parkour Background",
            "Family Guy Cutaway Overlay",
            "Let Him Cook",
            "Unemployed",
            "Diddy Blud",
            "Domer",
            "Olive Delights",
            "Agartha",
            "Eye Of Rah",
            "Pattern Recognition",
            "Why Is He Lying",
            "Our Brains Are Shrinking",
            "Plankton Ahhh",
            "Clash Royal Audios",
            "Hamster",
            "King Von",
            "Bing Chilling",
            "Opium Bird",
            "1 2 buckle my shoe",
            "Bite of 87’",
            "Labubu",
            "Dubai Chocolate"
          ]
        }
      ]
    },
    {
      "name": "Movies",
      "icon": "Clapperboard",
      "id": "movies",
      "categories": [
        {
          "name": "Comedy",
          "icon": "Popcorn",
          "id": "comedy",
          "words": [
            "Zoolander",
            "Legally Blonde",
            "Freaky Friday",
            "White Chicks",
            "Scary Movie",
            "Austin Powers",
            "Monty Python and the Holy Grail",
            "The Naked Gun",
            "Airplane!",
            "School of Rock",
            "Nacho Libre",
            "Bridesmaids",
            "The Heat",
            "Grown Ups",
            "Home Alone",
            "Ferris Bueller’s Day Off",
            "The Princess Bride",
            "Mean Girls 2",
            "The Lego Movie",
            "The Lego Batman Movie",
            "Shrek",
            "Madagascar",
            "Despicable Me",
            "Minions",
            "Toy Story",
            "Monsters Inc",
            "Cars",
            "Ratatouille",
            "Turning Red",
            "Cloudy with a Chance of Meatballs",
            "Hotel Transylvania",
            "The Mitchells vs the Machines",
            "Paddington",
            "Mr. Bean",
            "Johnny English",
            "Shaun the Sheep Movie",
            "A Minecraft Movie",
            "The Bad Guys",
            "SpaceBalls",
            "Caddyshack",
            "Groundhog Day",
            "Space Jam",
            "Jumanji",
            "Napoleon Dynamite",
            "The Dictator",
            "Ace Ventura",
            "Dumb and Dumber",
            "Kung Fu Panda",
            "The Mask"
          ]
        },
        {
          "name": "Cinephile Favorites",
          "icon": "Award",
          "id": "cinephile_favs",
          "words": [
            "The Big Short",
            "American Psycho",
            "The Wolf of Wall Street",
            "Once Upon a Time in Hollywood",
            "Cast Away",
            "The Terminal",
            "The Godfather",
            "Goodfellas",
            "Scarface",
            "Casino",
            "Heat",
            "Taxi Driver",
            "Raging Bull",
            "Forrest Gump",
            "Titanic",
            "Donnie Darko",
            "No Country for Old Men",
            "There Will Be Blood",
            "The Social Network",
            "Oppenheimer",
            "Slumdog Millionaire",
            "Life of Pi",
            "Les Misérables",
            "La La Land",
            "Citizen Kane",
            "Casablanca",
            "The Shawshank Redemption",
            "Schindler’s List",
            "The Pianist",
            "A Beautiful Mind",
            "The Green Mile",
            "Gone with the Wind",
            "Moonlight",
            "Whiplash",
            "The Shape of Water",
            "Dunkirk",
            "Joker",
            "The Truman Show",
            "Fight Club",
            "The Prestige",
            "Memento",
            "Shutter Island",
            "Gone Girl",
            "Zodiac",
            "Se7en",
            "The Silence of the Lambs",
            "Her",
            "Lost in Translation",
            "Your Name",
            "Parasite",
            "Crouching Tiger Hidden Dragon",
            "Seven Samurai",
            "Marty Supreme",
            "Fantastic Mr. Fox",
            "Isle Of Dogs",
            "2001: A Space Odyssey",
            "Blade Runner",
            "Pulp Fiction",
            "Inception",
            "Interstellar",
            "The Dark Knight",
            "Oldboy",
            "Vertigo",
            "Psycho",
            "Lawrence of Arabia",
            "The Grand Budapest Hotel",
            "The Game",
            "Davinci Code",
            "Bullet Train"
          ]
        },
        {
          "name": "Marvel+DC",
          "icon": "ShieldAlert",
          "id": "marveldc",
          "words": [
            "Iron Man",
            "The Incredible Hulk",
            "Thor",
            "Captain America",
            "The Avengers",
            "Guardians of the Galaxy",
            "Ant-Man",
            "Doctor Strange",
            "Black Panther",
            "Captain Marvel",
            "Black Widow",
            "Eternals",
            "Shang-Chi",
            "Thunderbolts",
            "Spider-Man",
            "Into the Spider-Verse",
            "X-Men",
            "Logan",
            "Deadpool",
            "Fantastic Four",
            "Ghost Rider",
            "Daredevil",
            "Venom",
            "Morbius",
            "Big Hero 6",
            "Superman",
            "The Dark Knight",
            "Joker",
            "Man of Steel",
            "Batman v Superman",
            "Justice League",
            "Wonder Woman",
            "Aquaman",
            "The Flash",
            "Black Adam",
            "Shazam!",
            "Green Lantern",
            "Suicide Squad",
            "Birds of Prey",
            "Teenage Mutant Ninja Turtles",
            "The Lego Batman Movie",
            "DC League of Super-Pets"
          ]
        },
        {
          "name": "Sci-Fi/Fantasy",
          "icon": "Rocket",
          "id": "scifi__fantasy",
          "words": [
            "Iron Man",
            "The Incredible Hulk",
            "The Avengers",
            "Guardians of the Galaxy",
            "Spider-Man",
            "Batman Begins",
            "The Dark Knight",
            "Joker",
            "Superman",
            "Justice League",
            "Wonder Woman",
            "Aquaman",
            "The Flash",
            "Venom",
            "Fantastic Four",
            "The Incredibles",
            "Hellboy",
            "Megamind",
            "Teenage Mutant Ninja Turtles",
            "RoboCop",
            "The Mask",
            "Matilda",
            "Star Wars",
            "Dune",
            "Blade Runner",
            "The Matrix",
            "Inception",
            "Interstellar",
            "Arrival",
            "Everything Everywhere All at Once",
            "E.T.",
            "Back to the Future",
            "Jurassic Park",
            "Godzilla",
            "King Kong",
            "Pacific Rim",
            "Tron",
            "Avatar",
            "Ready Player One",
            "The Terminator",
            "Planet of the Apes",
            "Alien",
            "Predator",
            "Harry Potter",
            "Fantastic Beasts",
            "The Lord of the Rings",
            "The Hobbit",
            "Ghostbusters",
            "The Martian",
            "The Iron Giant",
            "Maze Runner",
            "Oblivion",
            "Edge of Tomorrow",
            "Valerian and the City of a Thousand Planets"
          ]
        },
        {
          "name": "Horror",
          "icon": "Skull",
          "id": "horror",
          "words": [
            "Smile",
            "Scream",
            "Se7en",
            "Zodiac",
            "Shutter Island",
            "Get Out",
            "Midsommar",
            "The Shining",
            "It",
            "Halloween",
            "Saw",
            "Parasite",
            "Train to Busan",
            "Psycho",
            "The Sixth Sense",
            "Final Destination",
            "World War Z",
            "I Am Legend",
            "Alien",
            "Predator",
            "American Psycho",
            "The Orphanage",
            "The Menu",
            "The Invisible Man",
            "Donnie Darko",
            "Five Nights At Freddie’s",
            "Frankenstein",
            "The Gremlins",
            "Jaws",
            "Megan 2.0",
            "Monster House",
            "Weapons",
            "A Quiet Place"
          ]
        },
        {
          "name": "Animated",
          "icon": "Pencil",
          "id": "animated",
          "words": [
            "Snow White and the Seven Dwarfs",
            "Pinocchio",
            "Dumbo",
            "Bambi",
            "Cinderella",
            "Alice in Wonderland",
            "Peter Pan",
            "Sleeping Beauty",
            "101 Dalmatians",
            "The Jungle Book",
            "Robin Hood",
            "The Little Mermaid",
            "Beauty and the Beast",
            "Aladdin",
            "The Lion King",
            "Mulan",
            "Tarzan",
            "Lilo & Stitch",
            "Treasure Planet",
            "Tangled",
            "Wreck-It Ralph",
            "Frozen",
            "Big Hero 6",
            "Zootopia",
            "Moana",
            "Toy Story",
            "A Bug’s Life",
            "Monsters",
            "Inc.",
            "Finding Nemo",
            "The Incredibles",
            "Cars",
            "Ratatouille",
            "WALL·E",
            "Up",
            "Inside Out",
            "Coco",
            "Shrek",
            "Madagascar",
            "Kung Fu Panda",
            "How to Train Your Dragon",
            "Megamind",
            "The Croods",
            "Trolls",
            "The Bad Guys",
            "Puss in Boots",
            "Despicable Me",
            "The Secret Life of Pets",
            "Sing",
            "The Lorax",
            "Ice Age",
            "Rio",
            "The Iron Giant",
            "The Lego Movie",
            "Coraline",
            "Spider-Man: Into the Spider-Verse",
            "The Mitchells vs. the Machines",
            "Hotel Transylvania",
            "Spirited Away",
            "My Neighbor Totoro",
            "Howl’s Moving Castle",
            "Akira",
            "Your Name",
            "NeZha",
            "Piece By Piece",
            "Tin Tin",
            "Fantastic Mr. Fox",
            "Kpop Demon Hunters"
          ]
        },
        {
          "name": "Game Adaptations",
          "icon": "Gamepad",
          "id": "game_adaptations",
          "words": [
            "The Super Mario Bros. Movie",
            "A Minecraft Movie",
            "Free Guy",
            "Assassin’s Creed",
            "Detective Pikachu",
            "Sonic the Hedgehog",
            "Resident Evil",
            "Tomb Raider",
            "The Angry Birds Movie",
            "Five Nights at Freddy’s"
          ]
        },
        {
          "name": "Book Adaptations",
          "icon": "BookOpen",
          "id": "book_adaptations",
          "words": [
            "Harry Potter",
            "The Lord of the Rings",
            "The Hobbit",
            "The Chronicles of Narnia",
            "Percy Jackson",
            "The Hunger Games",
            "Divergent",
            "The Maze Runner",
            "Jurassic Park",
            "Jaws",
            "The Godfather",
            "The Shawshank Redemption",
            "Forrest Gump",
            "Fight Club",
            "No Country for Old Men",
            "Pride & Prejudice",
            "Little Women",
            "Wuthering Heights",
            "A Christmas Carol",
            "The Princess Bride",
            "The NeverEnding Story",
            "The Wizard of Oz",
            "Mary Poppins",
            "Peter Pan",
            "Alice in Wonderland",
            "Charlie and the Chocolate Factory",
            "Matilda",
            "The BFG",
            "James and the Giant Peach",
            "Coraline",
            "The Polar Express",
            "Howl’s Moving Castle",
            "The Hunger Games",
            "The Devil Wears Prada",
            "Legally Blonde",
            "The Princess Diaries",
            "Hidden Figures",
            "Moneyball",
            "The Social Network",
            "The Martian",
            "Dune",
            "Ready Player One",
            "Ender’s Game",
            "The Jungle Book",
            "Tarzan",
            "The Little Mermaid",
            "Pinocchio",
            "Bambi",
            "Sleeping Beauty",
            "Snow White",
            "Cinderella",
            "Beauty and the Beast",
            "Sherlock Holmes",
            "Dracula",
            "Frankenstein",
            "The Shining",
            "Stand by Me",
            "The Great Gatsby",
            "Life of Pi",
            "Slumdog Millionaire",
            "To Kill a Mockingbird",
            "The Old Man and the Sea",
            "Jason Bourne",
            "Da Vinci Code"
          ]
        },
        {
          "name": "Action/Thriller",
          "icon": "Target",
          "id": "action_thriller",
          "words": [
            "James Bond",
            "The Bourne Identity",
            "Mission: Impossible",
            "Heat",
            "John Wick",
            "The Equalizer",
            "RoboCop",
            "Fast and Furious",
            "Inception",
            "Interstellar",
            "Dunkirk",
            "Now You See Me",
            "Independence Day",
            "Ocean’s Eleven",
            "Tenet",
            "Edge of Tomorrow",
            "Oblivion",
            "Die Hard",
            "Bad Boys",
            "Top Gun",
            "Knives Out",
            "Joker",
            "Godfather",
            "The Meg",
            "Pacific Rim"
          ]
        }
      ]
    },
    {
      "name": "TV Shows",
      "icon": "Tv",
      "id": "tv_shows",
      "categories": [
        {
          "name": "Drama",
          "icon": "Award",
          "id": "drama",
          "words": [
            "The Sopranos",
            "The Wire",
            "Mad Men",
            "Breaking Bad",
            "Better Call Saul",
            "Six Feet Under",
            "Succession",
            "Chernobyl",
            "House of Cards",
            "The Handmaid’s Tale",
            "True Detective",
            "Fargo",
            "Narcos",
            "Peaky Blinders",
            "The Queen’s Gambit",
            "Severance",
            "Orange Is the New Black",
            "The Bear",
            "Grey’s Anatomy",
            "House",
            "Suits",
            "The Boys"
          ]
        },
        {
          "name": "Crime/Mystery",
          "icon": "Fingerprint",
          "id": "crime_mystery",
          "words": [
            "Breaking Bad",
            "Better Call Saul",
            "Dexter",
            "CSI: Crime Scene Investigation",
            "True Detective",
            "Fargo",
            "Sherlock",
            "House of Cards",
            "Narcos",
            "Peaky Blinders",
            "The X-Files",
            "Twin Peaks",
            "Black Mirror",
            "Prison Break"
          ]
        },
        {
          "name": "Sci-Fi/Fantasy",
          "icon": "Rocket",
          "id": "scifi_fantasy",
          "words": [
            "Game of Thrones",
            "Star Trek",
            "Westworld",
            "Lost",
            "Lost in Space",
            "The 3-Body Problem",
            "Stranger Things",
            "Avatar: The Last Airbender",
            "The Walking Dead",
            "Black Mirror",
            "Cyberpunk: Edgerunners",
            "Alien Worlds",
            "Pluribus",
            "Wednesday",
            "The Boys",
            "Clone Wars",
            "Percy Jackson",
            "It: Welcome to Derry"
          ]
        },
        {
          "name": "Comedy",
          "icon": "Popcorn",
          "id": "comedy",
          "words": [
            "Seinfeld",
            "The Office (US)",
            "Friends",
            "The Big Bang Theory",
            "Brooklyn Nine-Nine",
            "Community",
            "Curb Your Enthusiasm",
            "Full House",
            "Malcolm in the Middle",
            "How I Met Your Mother",
            "Modern Family",
            "Saturday Night Live",
            "The Daily Show",
            "Fresh Off the Boat",
            "Everybody Hates Chris",
            "Rookie",
            "Peacemaker",
            "young Sheldon"
          ]
        },
        {
          "name": "Animation",
          "icon": "Pencil",
          "id": "animation",
          "words": [
            "The Simpsons",
            "South Park",
            "Rick and Morty",
            "Family Guy",
            "American Dad",
            "BoJack Horseman",
            "Big Mouth",
            "The Boondocks",
            "Futurama",
            "Regular Show",
            "Samurai Jack",
            "Rabbids",
            "Adventure Time",
            "SpongeBob SquarePants",
            "Shaun the Sheep",
            "Wallace and Gromit",
            "Archer",
            "Daniel Tiger’s Neighborhood",
            "The Magic School Bus",
            "Scooby-Doo",
            "Gravity Falls",
            "Teen Titans",
            "Tom and Jerry",
            "Invincible",
            "Arcane",
            "My Little Pony",
            "Phineas and Ferb",
            "Ben Ten",
            "Dora the explorer",
            "Lego ninjago"
          ]
        },
        {
          "name": "Anime",
          "icon": "Sparkles",
          "id": "anime",
          "words": [
            "Dragon Ball Z",
            "Naruto",
            "Naruto Shippuden",
            "One Piece",
            "Bleach",
            "Pokémon",
            "Attack on Titan",
            "Demon Slayer",
            "Jujutsu Kaisen",
            "My Hero Academia",
            "Chainsaw Man",
            "Spy x Family",
            "Blue Lock",
            "Death Note",
            "Neon Genesis Evangelion",
            "Dr Stone",
            "Hunter x Hunter",
            "JoJo’s Bizarre Adventure",
            "Frieren",
            "One Punch Man",
            "detective Conan"
          ]
        },
        {
          "name": "Teen Girls",
          "icon": "Heart",
          "id": "teen_girls",
          "words": [
            "Euphoria",
            "Wednesday",
            "Gossip Girl",
            "Sex and the City",
            "Bridgerton",
            "Pretty Little Liars",
            "Gilmore Girls",
            "Love Island",
            "The Kardashians",
            "My Little Pony",
            "Never Have I Ever",
            "The Summer I Turned Pretty",
            "Too Hot to Handle",
            "The Vampire Diaries"
          ]
        },
        {
          "name": "Kids",
          "icon": "Baby",
          "id": "kids",
          "words": [
            "Sesame Street",
            "Paw Patrol",
            "Avatar: The Last Airbender",
            "Pokémon",
            "Rabbids",
            "Teen Titans",
            "Tom and Jerry",
            "Shaun the Sheep",
            "Wallace and Gromit",
            "Teen Titans",
            "Daniel Tiger’s Neighborhood",
            "The Magic School Bus",
            "Scooby-Doo",
            "My Little Pony",
            "Gravity Falls"
          ]
        },
        {
          "name": "Reality/Documentary",
          "icon": "Video",
          "id": "reality_documentary",
          "words": [
            "Love Island",
            "Blue Planet II",
            "Alien Worlds",
            "Prehistoric Planet",
            "The Kardashians",
            "Is It Cake",
            "Beast Games",
            "Too Hot to Handle",
            "Hell’s Kitchen",
            "MasterChef",
            "Floor Is Lava",
            "Our Planet"
          ]
        }
      ]
    }
  ]
}